main.py
pysondb_show-0.1.0.dist-info/LICENSE
pysondb_show-0.1.0.dist-info/METADATA
pysondb_show-0.1.0.dist-info/WHEEL
pysondb_show-0.1.0.dist-info/entry_points.txt
pysondb_show-0.1.0.dist-info/top_level.txt
pysondb_show-0.1.0.dist-info/RECORD
