Metadata-Version: 2.1
Name: pysondb-show
Version: 0.1.0
Summary: The beautiful table plugin for pysondb
Home-page: https://github.com/Adwaith-Rajesh/pysondb-show
Author: Adwaith-Rajesh
Author-email: adwaithrajesh3180@gmail.com
License: MIT
Platform: UNKNOWN
Classifier: License :: OSI Approved :: MIT License
Classifier: Programming Language :: Python :: 3
Classifier: Programming Language :: Python :: 3 :: Only
Classifier: Programming Language :: Python :: 3.6
Classifier: Programming Language :: Python :: 3.7
Classifier: Programming Language :: Python :: 3.8
Classifier: Programming Language :: Python :: 3.9
Requires-Python: >=3.6.1
License-File: LICENSE
Requires-Dist: beautifultable
